pydymenu/__init__.py
pydymenu/__main__.py
pydymenu/console.py
pydymenu/demo_data.py
pydymenu/exceptions.py
pydymenu/fzf.py
pydymenu/menu.py
pydymenu/rofi.py
pydymenu/system.py
pydymenu/demo/__init__.py
pydymenu/demo/fzf.py
pydymenu/demo/rofi.py
pydymenu-0.5.2.dist-info/LICENSE.md
pydymenu-0.5.2.dist-info/METADATA
pydymenu-0.5.2.dist-info/WHEEL
pydymenu-0.5.2.dist-info/top_level.txt
pydymenu-0.5.2.dist-info/RECORD
