Metadata-Version: 2.1
Name: pydymenu
Version: 0.5.2
Summary: A pythonic wrapper interface for fzf, dmenu, and rofi.
Home-page: https://github.com/gikeymarcia/pydymenu
Author: Mikey Garcia
Author-email: gikeymarcia@gmail.com
License: GPL-3.0
Platform: UNKNOWN
Requires-Dist: rich
